/*
 * instructions.c
 *
 *  Created on: 25/01/2011
 *      Author: joaofreitas
 */

#include "executeInstructions.h"
#include "../structures/mnemonics.h"



void initOperands() {

	op_info[0x32].func = func_aaload;
	op_info[0x53].func = func_aastore;
	op_info[0x01].func = func_aconst_null;
	op_info[0x19].func = func_aload;
	op_info[0x2a].func = func_aload_0;
	op_info[0x2b].func = func_aload_1;
	op_info[0x2c].func = func_aload_2;
	op_info[0x2d].func = func_aload_3;
	op_info[0xbd].func = func_anewarray;
	op_info[0xb0].func = func_areturn;
	op_info[0xbe].func = func_arraylength;
	op_info[0x3a].func = func_astore;
	op_info[0x4b].func = func_astore_0;
	op_info[0x4c].func = func_astore_1;
	op_info[0x4d].func = func_astore_2;
	op_info[0x4e].func = func_astore_3;
	op_info[0xbf].func = func_athrow;
	op_info[0x33].func = func_baload;
	op_info[0x54].func = func_bastore;
	op_info[0x10].func = func_bipush;
	op_info[0x34].func = func_caload;
	op_info[0x55].func = func_castore;
	op_info[0xc0].func = func_checkcast;
	op_info[0x90].func = func_d2f;
	op_info[0x8e].func = func_d2i;
	op_info[0x8f].func = func_d2l;
	op_info[0x63].func = func_dadd;
	op_info[0x31].func = func_daload;
	op_info[0x52].func = func_dastore;
	op_info[0x98].func = func_dcmpg;
	op_info[0x97].func = func_dcmpl;
	op_info[0x0e].func = func_dconst_0;
	op_info[0x0f].func = func_dconst_1;
	op_info[0x6f].func = func_ddiv;
	op_info[0x18].func = func_dload;
	op_info[0x26].func = func_dload_0;
	op_info[0x27].func = func_dload_1;
	op_info[0x28].func = func_dload_2;
	op_info[0x29].func = func_dload_3;
	op_info[0x6b].func = func_dmul;
	op_info[0x77].func = func_dneg;
	op_info[0x73].func = func_drem;
	op_info[0xaf].func = func_dreturn;
	op_info[0x39].func = func_dstore;
	op_info[0x47].func = func_dstore_0;
	op_info[0x48].func = func_dstore_1;
	op_info[0x49].func = func_dstore_2;
	op_info[0x4a].func = func_dstore_3;
	op_info[0x67].func = func_dsub;
	op_info[0x59].func = func_dup;
	op_info[0x5a].func = func_dup_x1;
	op_info[0x5b].func = func_dup_x2;
	op_info[0x5c].func = func_dup2;
	op_info[0x5d].func = func_dup2_x1;
	op_info[0x5e].func = func_dup2_x2;
	op_info[0x8d].func = func_f2d;
	op_info[0x8b].func = func_f2i;
	op_info[0x8c].func = func_f2l;
	op_info[0x62].func = func_fadd;
	op_info[0x30].func = func_faload;
	op_info[0x51].func = func_fastore;
	op_info[0x96].func = func_fcmpg;
	op_info[0x95].func = func_fcmpl;
	op_info[0x0b].func = func_fconst_0;
	op_info[0x0c].func = func_fconst_1;
	op_info[0x0d].func = func_fconst_2;
	op_info[0x6e].func = func_fdiv;
	op_info[0x17].func = func_fload;
	op_info[0x22].func = func_fload_0;
	op_info[0x23].func = func_fload_1;
	op_info[0x24].func = func_fload_2;
	op_info[0x25].func = func_fload_3;
	op_info[0x6a].func = func_fmul;
	op_info[0x76].func = func_fneg;
	op_info[0x72].func = func_frem;
	op_info[0xae].func = func_freturn;
	op_info[0x38].func = func_fstore;
	op_info[0x43].func = func_fstore_0;
	op_info[0x44].func = func_fstore_1;
	op_info[0x45].func = func_fstore_2;
	op_info[0x46].func = func_fstore_3;
	op_info[0x66].func = func_fsub;
	op_info[0xb4].func = func_getfield;
	op_info[0xb2].func = func_getstatic;
	op_info[0xa7].func = func_goto;
	op_info[0xc8].func = func_goto_w;
	op_info[0x91].func = func_i2b;
	op_info[0x92].func = func_i2c;
	op_info[0x87].func = func_i2d;
	op_info[0x86].func = func_i2f;
	op_info[0x85].func = func_i2l;
	op_info[0x93].func = func_i2s;
	op_info[0x60].func = func_iadd;
	op_info[0x2e].func = func_iaload;
	op_info[0x7e].func = func_iand;
	op_info[0x4f].func = func_iastore;
	op_info[0x02].func = func_iconst_m1;
	op_info[0x03].func = func_iconst_0;
	op_info[0x04].func = func_iconst_1;
	op_info[0x05].func = func_iconst_2;
	op_info[0x06].func = func_iconst_3;
	op_info[0x07].func = func_iconst_4;
	op_info[0x08].func = func_iconst_5;
	op_info[0x6c].func = func_idiv;
	op_info[0xa5].func = func_if_acmpeq;
	op_info[0xa6].func = func_if_acmpne;
	op_info[0x9f].func = func_if_icmpeq;
	op_info[0xa0].func = func_if_icmpne;
	op_info[0xa1].func = func_if_icmplt;
	op_info[0xa2].func = func_if_icmpge;
	op_info[0xa3].func = func_if_icmpgt;
	op_info[0xa4].func = func_if_icmple;
	op_info[0x99].func = func_ifeq;
	op_info[0x9a].func = func_ifne;
	op_info[0x9b].func = func_iflt;
	op_info[0x9c].func = func_ifge;
	op_info[0x9d].func = func_ifgt;
	op_info[0x9e].func = func_ifle;
	op_info[0xc7].func = func_ifnonnull;
	op_info[0xc6].func = func_ifnull;
	op_info[0x84].func = func_iinc;
	op_info[0x15].func = func_iload;
	op_info[0x1a].func = func_iload_0;
	op_info[0x1b].func = func_iload_1;
	op_info[0x1c].func = func_iload_2;
	op_info[0x1d].func = func_iload_3;
	op_info[0x68].func = func_imul;
	op_info[0x74].func = func_ineg;
	op_info[0xc1].func = func_instanceof;
	op_info[0xb9].func = func_invokeinterface;
	op_info[0xb7].func = func_invokespecial;
	op_info[0xb8].func = func_invokestatic;
	op_info[0xb6].func = func_invokevirtual;
	op_info[0x80].func = func_ior;
	op_info[0x70].func = func_irem;
	op_info[0xac].func = func_ireturn;
	op_info[0x78].func = func_ishl;
	op_info[0x7a].func = func_ishr;
	op_info[0x36].func = func_istore;
	op_info[0x3b].func = func_istore_0;
	op_info[0x3c].func = func_istore_1;
	op_info[0x3d].func = func_istore_2;
	op_info[0x3e].func = func_istore_3;
	op_info[0x64].func = func_isub;
	op_info[0x7c].func = func_iushr;
	op_info[0x82].func = func_ixor;
	op_info[0xa8].func = func_jsr;
	op_info[0xc9].func = func_jsr_w;
	op_info[0x8a].func = func_l2d;
	op_info[0x89].func = func_l2f;
	op_info[0x88].func = func_l2i;
	op_info[0x61].func = func_ladd;
	op_info[0x2f].func = func_laload;
	op_info[0x7f].func = func_land;
	op_info[0x50].func = func_lastore;
	op_info[0x94].func = func_lcmp;
	op_info[0x09].func = func_lconst_0;
	op_info[0x0a].func = func_lconst_1;
	op_info[0x12].func = func_ldc;
	op_info[0x13].func = func_ldc_w;
	op_info[0x14].func = func_ldc2_w;
	op_info[0x6d].func = func_ldiv;
	op_info[0x16].func = func_lload;
	op_info[0x1e].func = func_lload_0;
	op_info[0x1f].func = func_lload_1;
	op_info[0x20].func = func_lload_2;
	op_info[0x21].func = func_lload_3;
	op_info[0x69].func = func_lmul;
	op_info[0x75].func = func_lneg;
	op_info[0xab].func = func_lookupswitch;
	op_info[0x81].func = func_lor;
	op_info[0x71].func = func_lrem;
	op_info[0xad].func = func_lreturn;
	op_info[0x79].func = func_lshl;
	op_info[0x7b].func = func_lshr;
	op_info[0x37].func = func_lstore;
	op_info[0x3f].func = func_lstore_0;
	op_info[0x40].func = func_lstore_1;
	op_info[0x41].func = func_lstore_2;
	op_info[0x42].func = func_lstore_3;
	op_info[0x65].func = func_lsub;
	op_info[0x7d].func = func_lushr;
	op_info[0x83].func = func_lxor;
	op_info[0xc2].func = func_monitorenter;
	op_info[0xc3].func = func_monitorexit;
	op_info[0xc5].func = func_multianewarray;
	op_info[0xbb].func = func_new;
	op_info[0xbc].func = func_newarray;
	op_info[0x00].func = func_nop;
	op_info[0x57].func = func_pop;
	op_info[0x58].func = func_pop2;
	op_info[0xb5].func = func_putfield;
	op_info[0xb3].func = func_putstatic;
	op_info[0xa9].func = func_ret;
	op_info[0xb1].func = func_return;
	op_info[0x35].func = func_saload;
	op_info[0x56].func = func_sastore;
	op_info[0x11].func = func_sipush;
	op_info[0x5f].func = func_swap;
	op_info[0xaa].func = func_tableswitch;
	op_info[0xc4].func = func_wide;
	op_info[0xca].func = func_breakpoint;
	op_info[0xfe].func = func_impdep1;
	op_info[0xff].func = func_impdep2;
	/*op_info[0xba].func = func_xxxunusedxxx;*/
}
